slurmomatic/__init__.py
slurmomatic/core.py
slurmomatic/hpo.py
slurmomatic/ml.py
slurmomatic/utils.py
slurmomatic-0.1.1.dist-info/METADATA
slurmomatic-0.1.1.dist-info/WHEEL
slurmomatic-0.1.1.dist-info/entry_points.txt
slurmomatic-0.1.1.dist-info/licenses/LICENSE
slurmomatic-0.1.1.dist-info/RECORD
