Metadata-Version: 2.4
Name: slurmomatic
Version: 0.1.1
Summary: custom decorator to turn any function slurm-deployable. Can submit multiple jobs and multiple job_arrays
Author-email: eric wang <ehjwang@gmail.com>
License-File: LICENSE
Requires-Python: >=3.10
Requires-Dist: numpy==1.26
Requires-Dist: optuna>=4.2.1
Requires-Dist: scikit-learn==1.5.2
Requires-Dist: setuptools>=78.0.1
Requires-Dist: submitit>=1.5.2
